zignpay/__init__.py
zignpay/momo.py
zignpay-0.2.1.dist-info/licenses/LICENCE
zignpay-0.2.1.dist-info/METADATA
zignpay-0.2.1.dist-info/WHEEL
zignpay-0.2.1.dist-info/entry_points.txt
zignpay-0.2.1.dist-info/top_level.txt
zignpay-0.2.1.dist-info/RECORD
