Metadata-Version: 2.4
Name: zignpay
Version: 0.2.1
Summary: A package to manage mobile payments using the MTN MoMo and Orange Money APIs
Author-email: Kevelino <kevinnengou02@gmail.com>
Maintainer-email: Kevelino <kevinnengou02@gmail.com>
Project-URL: Homepage, https://github.com/kevelino/zignpay
Project-URL: Bug Reports, https://github.com/kevelino/zignpay/issues
Project-URL: Funding, https://donate.pypi.org
Project-URL: Source, https://github.com/kevelino/zignpay/
Keywords: sample,setuptools,development
Requires-Python: >=3.8
License-File: LICENCE
Dynamic: license-file
